byteforge_telegram/__init__.py
byteforge_telegram/cli.py
byteforge_telegram/models.py
byteforge_telegram/notifier.py
byteforge_telegram/webhook.py
byteforge_telegram-0.1.3.dist-info/METADATA
byteforge_telegram-0.1.3.dist-info/WHEEL
byteforge_telegram-0.1.3.dist-info/entry_points.txt
byteforge_telegram-0.1.3.dist-info/licenses/LICENSE
byteforge_telegram-0.1.3.dist-info/RECORD
