Metadata-Version: 2.4
Name: byteforge-telegram
Version: 0.1.3
Summary: Generic Telegram bot notification and webhook management library
Project-URL: Homepage, https://github.com/jmazzahacks/byteforge-telegram
Project-URL: Repository, https://github.com/jmazzahacks/byteforge-telegram
Project-URL: Issues, https://github.com/jmazzahacks/byteforge-telegram/issues
Author: Jason Byteforge
License: MIT
License-File: LICENSE
Keywords: bot,notifications,telegram,webhook
Classifier: Development Status :: 4 - Beta
Classifier: Intended Audience :: Developers
Classifier: License :: OSI Approved :: MIT License
Classifier: Programming Language :: Python :: 3
Classifier: Programming Language :: Python :: 3.9
Classifier: Programming Language :: Python :: 3.10
Classifier: Programming Language :: Python :: 3.11
Classifier: Programming Language :: Python :: 3.12
Classifier: Programming Language :: Python :: 3.13
Classifier: Topic :: Communications :: Chat
Classifier: Topic :: Software Development :: Libraries :: Python Modules
Requires-Python: >=3.9
Requires-Dist: python-telegram-bot>=20.0
Requires-Dist: requests>=2.31.0
Provides-Extra: dev
Requires-Dist: black>=23.0; extra == 'dev'
Requires-Dist: isort>=5.0; extra == 'dev'
Requires-Dist: mypy>=1.0; extra == 'dev'
Requires-Dist: pytest-asyncio>=0.21.0; extra == 'dev'
Requires-Dist: pytest-cov>=4.0; extra == 'dev'
Requires-Dist: pytest>=7.0; extra == 'dev'
